setup.py
bin/twins
twins/__init__.py
twins/bridge.py
twins/ics.py
twins/kdb.py
twins/misc.py
twins/twins.py
twins.egg-info/PKG-INFO
twins.egg-info/SOURCES.txt
twins.egg-info/dependency_links.txt
twins.egg-info/requires.txt
twins.egg-info/top_level.txt