Metadata-Version: 1.1
Name: twins
Version: 1.1.1
Summary: Command-line interface to Univ. of Tsukuba'scourse registration system
Home-page: https://github.com/coins13/twins
Author: UNKNOWN
Author-email: UNKNOWN
License: UNKNOWN
Platform: UNKNOWN
Classifier: Operating System :: POSIX
Classifier: Environment :: Console
Classifier: Development Status :: 5 - Production/Stable
Classifier: License :: OSI Approved :: GNU General Public License v2 (GPLv2)
Classifier: Topic :: Utilities
